cfcli/__init__.py
cfcli/cf.py
cfcli/cfcli.py
cfcli/cli.py
cfcli-0.0.2.dist-info/DESCRIPTION.rst
cfcli-0.0.2.dist-info/METADATA
cfcli-0.0.2.dist-info/RECORD
cfcli-0.0.2.dist-info/WHEEL
cfcli-0.0.2.dist-info/entry_points.txt
cfcli-0.0.2.dist-info/metadata.json
cfcli-0.0.2.dist-info/top_level.txt
